README.rst
setup.cfg
setup.py
polyglot/__init__.py
polyglot/upload.py
polyglot_bitcoin.egg-info/PKG-INFO
polyglot_bitcoin.egg-info/SOURCES.txt
polyglot_bitcoin.egg-info/dependency_links.txt
polyglot_bitcoin.egg-info/requires.txt
polyglot_bitcoin.egg-info/top_level.txt
tests/__init__.py
tests/test_polyglot.py