Metadata-Version: 2.1
Name: polyglot-bitcoin
Version: 0.0.1
Summary: Bitcoin protocols made easy.
Home-page: https://github.com/AustEcon/polyglot
Author: AustEcon
Author-email: AustEcon0922@gmail.com
Maintainer: AustEcon
Maintainer-email: AustEcon0922@gmail.com
License: MIT
Download-URL: https://github.com/AustEcon/polyglot/tarball/0.0.1
Keywords: polyglot,metanet,bitcoin sv,bsv,bitsv,cryptocurrency,payments,tools,wallet,bitcoin
Platform: UNKNOWN
Classifier: Development Status :: 3 - Alpha
Classifier: Intended Audience :: Developers
Classifier: Intended Audience :: End Users/Desktop
Classifier: License :: OSI Approved :: MIT License
Classifier: Natural Language :: English
Classifier: Operating System :: OS Independent
Classifier: Programming Language :: Python :: 3.6
Classifier: Programming Language :: Python :: 3.7
Classifier: Programming Language :: Python :: Implementation :: CPython
Provides-Extra: cli
Provides-Extra: cache
